pyblitzdg.cpython-39-x86_64-linux-gnu.so
pyblitzdg-1.0.3.dist-info/COPYING
pyblitzdg-1.0.3.dist-info/LICENSE
pyblitzdg-1.0.3.dist-info/METADATA
pyblitzdg-1.0.3.dist-info/WHEEL
pyblitzdg-1.0.3.dist-info/top_level.txt
pyblitzdg-1.0.3.dist-info/RECORD
pyblitzdg.libs/libvtkIOLegacy-7-cb306bbb.1.so.1
pyblitzdg.libs/libf77blas-75a5c7e0.so.3.0
pyblitzdg.libs/libsuitesparseconfig-9a3d3c5f.so.7.0.1
pyblitzdg.libs/libvtkCommonMath-7-84f9bd1b.1.so.1
pyblitzdg.libs/libmetis-7a774dbe.so
pyblitzdg.libs/libgfortran-139be63a.so.3.0.0
pyblitzdg.libs/libcxsparse-0f557c49.so.4.0.3
pyblitzdg.libs/libblitzdg-34b09a4e.so.1
pyblitzdg.libs/libvtksys-7-69889b0b.1.so.1
pyblitzdg.libs/libquadmath-2d0c479f.so.0.0.0
pyblitzdg.libs/libvtkCommonCore-7-7805343a.1.so.1
pyblitzdg.libs/libgfortran-2e0d59d6.so.5.0.0
pyblitzdg.libs/libgomp-f7e03b3e.so.1.0.0
pyblitzdg.libs/libvtkCommonMisc-7-cabc33e8.1.so.1
pyblitzdg.libs/libamd-d08cadcb.so.3.0.3
pyblitzdg.libs/libvtkIOCore-7-dfe97149.1.so.1
pyblitzdg.libs/liblapack-7aef6c42.so.3.0
pyblitzdg.libs/libumfpack-f8dd94a7.so.6.1.0
pyblitzdg.libs/libcamd-1c724aa6.so.3.0.3
pyblitzdg.libs/libvtkCommonTransforms-7-4906df18.1.so.1
pyblitzdg.libs/libcolamd-b5dd36db.so.3.0.3
pyblitzdg.libs/libboost_numpy39-e47e5503.so.1.81.0
pyblitzdg.libs/libvtkCommonSystem-7-7afa32ed.1.so.1
pyblitzdg.libs/libblas-f8db10e6.so.3.11.0
pyblitzdg.libs/libvtkCommonExecutionModel-7-4d19a924.1.so.1
pyblitzdg.libs/libcblas-70dd3697.so.3.0
pyblitzdg.libs/libvtkexpat-7-0003cd4f.1.so.1
pyblitzdg.libs/libvtkCommonDataModel-7-fe1fb0af.1.so.1
pyblitzdg.libs/libcholmod_cuda-1c6bb8b8.so.4.0.3
pyblitzdg.libs/libvtkIOXML-7-3737a9a7.1.so.1
pyblitzdg.libs/libcholmod-f82674b7.so.4.0.3
pyblitzdg.libs/libz-eb09ad1d.so.1.2.3
pyblitzdg.libs/libvtkIOXMLParser-7-aff40fe8.1.so.1
pyblitzdg.libs/libblitz-39c24a3e.so.0.0.0
pyblitzdg.libs/libvtkIOGeometry-7-03350744.1.so.1
pyblitzdg.libs/libboost_python39-31d7b678.so.1.81.0
pyblitzdg.libs/libvtkzlib-7-008ece1d.1.so.1
pyblitzdg.libs/libatlas-b6fb69b0.so.3.0
