Metadata-Version: 2.1
Name: pyblitzdg
Version: 1.0.3
Summary: Discontinuous Galerkin Finite Element Library and Solvers
Home-page: https://github.com/WQCG/blitzdg
Author: Derek Steinmoeller
Author-email: dsteinmo@gmail.com
License: UNKNOWN
Platform: manylinux2010
Platform: win64
Platform: macosx
Classifier: Programming Language :: Python :: 3
Classifier: License :: OSI Approved :: GNU General Public License v3 (GPLv3)
Classifier: Operating System :: POSIX :: Linux
